AUTHORS
INSTALL
LICENSE
MANIFEST.in
NOTICE
README
requirements.txt
setup.cfg
setup.py
docs/Makefile
docs/conf.py
docs/configuration.rst
docs/faq.rst
docs/index.rst
docs/installation.rst
docs/introduction.rst
docs/make.bat
docs/usage.rst
src/content_licenses/__init__.py
src/content_licenses/admin.py
src/content_licenses/fields.py
src/content_licenses/models.py
src/content_licenses/tests.py
src/content_licenses/fixtures/content_licenses.json
src/content_licenses/locale/el/LC_MESSAGES/django.mo
src/content_licenses/locale/el/LC_MESSAGES/django.po
src/content_licenses/templates/content_licenses/all-rights-reserved.html
src/content_licenses/templates/content_licenses/base-creative-commons.html
src/content_licenses/templates/content_licenses/base.html
src/content_licenses/templates/content_licenses/creative-commons-attribution-no-derivatives.html
src/content_licenses/templates/content_licenses/creative-commons-attribution-non-commercial-no-derivatives.html
src/content_licenses/templates/content_licenses/creative-commons-attribution-non-commercial-share-alike.html
src/content_licenses/templates/content_licenses/creative-commons-attribution-non-commercial.html
src/content_licenses/templates/content_licenses/creative-commons-attribution-share-alike.html
src/content_licenses/templates/content_licenses/creative-commons-attribution.html
src/content_licenses/templates/content_licenses/creative-commons-license-hyperlink.html
src/content_licenses/templates/content_licenses/default.html
src/content_licenses/templates/content_licenses/public-domain.html
src/content_licenses/templatetags/__init__.py
src/content_licenses/templatetags/content_licenses_tags.py
src/django_content_licenses.egg-info/PKG-INFO
src/django_content_licenses.egg-info/SOURCES.txt
src/django_content_licenses.egg-info/dependency_links.txt
src/django_content_licenses.egg-info/top_level.txt