Metadata-Version: 1.0
Name: django-content-licenses
Version: 0.2.3
Summary: django-content-licenses is a Django app that adds support for adding licensing information to content.
Home-page: http://www.codetrax.org/projects/django-content-licenses
Author: George Notaras
Author-email: gnot [at] g-loaded.eu
License: Apache License version 2
Download-URL: https://source.codetrax.org/hgroot/django-content-licenses
Platform: any
Classifier: Development Status :: 4 - Beta
Classifier: Environment :: Web Environment
Classifier: Framework :: Django
Classifier: Intended Audience :: Developers
Classifier: License :: OSI Approved :: Apache Software License
Classifier: Natural Language :: English
Classifier: Operating System :: OS Independent
Classifier: Programming Language :: Python
Classifier: Topic :: Internet :: WWW/HTTP :: Dynamic Content
Classifier: Topic :: Software Development :: Libraries :: Application Frameworks
Classifier: Topic :: Software Development :: Libraries :: Python Modules
